MANIFEST.in
README.rst
setup.cfg
setup.py
django_crossbar.egg-info/PKG-INFO
django_crossbar.egg-info/SOURCES.txt
django_crossbar.egg-info/dependency_links.txt
django_crossbar.egg-info/requires.txt
django_crossbar.egg-info/top_level.txt
djcb/__init__.py
djcb/admin.py
djcb/models.py
djcb/tests.py
djcb/utils.py
djcb/views.py
djcb/management/__init__.py
djcb/management/commands/__init__.py
djcb/management/commands/djcb_init.py
djcb/management/commands/_setup/backend.py.template
djcb/management/commands/_setup/celery.py.template
djcb/management/commands/_setup/config.json.template